vitrage_tempest_plugin/README.rst
vitrage_tempest_plugin/__init__.py
vitrage_tempest_plugin/config.py
vitrage_tempest_plugin/plugin.py
vitrage_tempest_plugin/services/__init__.py
vitrage_tempest_plugin/tests/__init__.py
vitrage_tempest_plugin/tests/base.py
vitrage_tempest_plugin/tests/utils.py
vitrage_tempest_plugin/tests/api/__init__.py
vitrage_tempest_plugin/tests/api/event/__init__.py
vitrage_tempest_plugin/tests/api/event/base.py
vitrage_tempest_plugin/tests/api/event/test_events.py
vitrage_tempest_plugin/tests/api/rca/__init__.py
vitrage_tempest_plugin/tests/api/rca/base.py
vitrage_tempest_plugin/tests/api/rca/test_rca.py
vitrage_tempest_plugin/tests/api/resources/__init__.py
vitrage_tempest_plugin/tests/api/resources/test_resources.py
vitrage_tempest_plugin/tests/api/services/__init__.py
vitrage_tempest_plugin/tests/api/services/test_service.py
vitrage_tempest_plugin/tests/api/templates/__init__.py
vitrage_tempest_plugin/tests/api/templates/base.py
vitrage_tempest_plugin/tests/api/templates/test_template.py
vitrage_tempest_plugin/tests/api/templates/test_template_v2.py
vitrage_tempest_plugin/tests/api/templates/test_template_v3.py
vitrage_tempest_plugin/tests/api/topology/__init__.py
vitrage_tempest_plugin/tests/api/topology/base.py
vitrage_tempest_plugin/tests/api/topology/test_topology.py
vitrage_tempest_plugin/tests/api/webhook/__init__.py
vitrage_tempest_plugin/tests/api/webhook/test_webhook.py
vitrage_tempest_plugin/tests/common/__init__.py
vitrage_tempest_plugin/tests/common/aodh_utils.py
vitrage_tempest_plugin/tests/common/cinder_utils.py
vitrage_tempest_plugin/tests/common/constants.py
vitrage_tempest_plugin/tests/common/general_utils.py
vitrage_tempest_plugin/tests/common/glance_utils.py
vitrage_tempest_plugin/tests/common/heat_utils.py
vitrage_tempest_plugin/tests/common/neutron_utils.py
vitrage_tempest_plugin/tests/common/nova_utils.py
vitrage_tempest_plugin/tests/common/tempest_clients.py
vitrage_tempest_plugin/tests/common/vitrage_utils.py
vitrage_tempest_plugin-6.7.0.dist-info/AUTHORS
vitrage_tempest_plugin-6.7.0.dist-info/LICENSE
vitrage_tempest_plugin-6.7.0.dist-info/METADATA
vitrage_tempest_plugin-6.7.0.dist-info/WHEEL
vitrage_tempest_plugin-6.7.0.dist-info/entry_points.txt
vitrage_tempest_plugin-6.7.0.dist-info/pbr.json
vitrage_tempest_plugin-6.7.0.dist-info/top_level.txt
vitrage_tempest_plugin-6.7.0.dist-info/RECORD
