Metadata-Version: 2.1
Name: vitrage-tempest-plugin
Version: 6.7.0
Summary: Tempest plugin for Vitrage project
Home-page: https://docs.openstack.org/tempest/latest/plugin-registry.html
Author: OpenStack
Author-email: openstack-discuss@lists.openstack.org
Classifier: Environment :: OpenStack
Classifier: Intended Audience :: Information Technology
Classifier: Intended Audience :: System Administrators
Classifier: License :: OSI Approved :: Apache Software License
Classifier: Operating System :: POSIX :: Linux
Classifier: Programming Language :: Python
Classifier: Programming Language :: Python :: 3
Classifier: Programming Language :: Python :: 3.8
Classifier: Programming Language :: Python :: 3.9
Classifier: Programming Language :: Python :: 3.10
Classifier: Programming Language :: Python :: 3.11
Classifier: Programming Language :: Python :: 3.12
License-File: LICENSE
License-File: AUTHORS
Requires-Dist: pbr !=2.1.0,>=2.0.0
Requires-Dist: aodhclient >=1.0.0
Requires-Dist: gnocchiclient >=3.3.1
Requires-Dist: PyYAML >=3.12
Requires-Dist: python-heatclient >=1.14.0
Requires-Dist: python-cinderclient >=3.3.0
Requires-Dist: python-dateutil >=2.5.3
Requires-Dist: python-keystoneclient >=3.15.0
Requires-Dist: python-neutronclient >=6.7.0
Requires-Dist: python-novaclient >=10.1.0
Requires-Dist: python-mistralclient >=3.3.0
Requires-Dist: python-glanceclient >=2.8.0
Requires-Dist: python-vitrageclient >=2.0.0
Requires-Dist: oslo.config >=5.2.0
Requires-Dist: oslo.serialization !=2.19.1,>=2.18.0
Requires-Dist: oslo.log >=3.36.0
Requires-Dist: oslo.utils >=3.36.0
Requires-Dist: testtools >=2.2.0
Requires-Dist: oslotest >=3.2.0
Requires-Dist: tempest >=17.1.0
Requires-Dist: networkx >=2.3
